Workbook

Sheet 二星词频（带音标与简明义项）
A1: # | B1: 单词 | C1: 解释
A2: 1 | B2: sour | C2: =VLOOKUP(B2,Sheet1!$A:$B,2,0) -> /saʊə//'saʊɚ/ - adj. 有酸味的, 酸的 - 有发酵味道的, 酸腐的, 馊的 - 坏脾气的; 别扭的 - vt. & vi. (使某物)变酸, 变馊; (使某人)阴郁 比较级: sourer, sourest 形容词: sourish 副 词: sourly 名 词: sourness...
A3: 2 | B3: freely | C3: =VLOOKUP(B3,Sheet1!$A:$B,2,0) -> /ˈfri:lɪ//'frili/ adv. 自由地,随意地,免费地
A4: 3 | B4: educated | C4: =VLOOKUP(B4,Sheet1!$A:$B,2,0) -> /'edjʊkeɪtɪd//'ɛdʒə'ketɪd/ - adj. 有教养的；受过教育的 - v. 教导；训练；培育（educate的过去分词形式）
A5: 4 | B5: engaged | C5: =VLOOKUP(B5,Sheet1!$A:$B,2,0) -> /ɪn'geɪdʒd//ɪn'gedʒd/ - adj. 使用中的，忙碌的 - v. 约定；保证；同…订婚（engage的过去分词）
A6: 5 | B6: prohibit | C6: =VLOOKUP(B6,Sheet1!$A:$B,2,0) -> /prə(ʊ)'hɪbɪt//prə'hɪbɪt/ vt. 阻止，禁止 时 态: prohibited, prohibiting, prohibits
A7: 6 | B7: tan | C7: =VLOOKUP(B7,Sheet1!$A:$B,2,0) -> /tæn//tæn/ - n. 黄褐色, 棕黄色 - vt. & vi. (使)晒成棕褐色 - vt. 硝制(皮革) TANabbr. total ammonia nitrogen 总氨氮 时 态: tanned, tanning, tans 形容词: tannish...
A8: 7 | B8: dispose | C8: =VLOOKUP(B8,Sheet1!$A:$B,2,0) -> /dɪ'spəʊz//dɪ'spoz/ - vt. 处理；处置；安排 - vi. 处理；安排；（能够）决定 - n. 处置；性情 时 态: disposed, disposing, disposes 名 词: disposer
A9: 8 | B9: voyage | C9: =VLOOKUP(B9,Sheet1!$A:$B,2,0) -> /'vɒɪɪdʒ//'vɔɪɪdʒ/ - n. 航行；航程；旅行记 - vi. 航海；航行 - vt. 飞过；渡过 时 态: voyaged, voyaging, voyages 名 词: voyager
A10: 9 | B10: doll | C10: =VLOOKUP(B10,Sheet1!$A:$B,2,0) -> /dɔl//dɑl/ - n. 洋娃娃；玩偶；无头脑的美丽女人 - vt. 把…打扮得花枝招展 Doll多尔(女子名, Dorothy 的昵称)
A11: 10 | B11: copper | C11: =VLOOKUP(B11,Sheet1!$A:$B,2,0) -> /'kɒpə//'kɑpɚ/ - n. 铜；铜币；[俚]警察 - adj. 铜的 - vt. 镀铜于 时 态: coppered, coppering, coppers 形容词: coppery
A12: 11 | B12: obsession | C12: =VLOOKUP(B12,Sheet1!$A:$B,2,0) -> /əb'seʃ(ə)n//əbˈsɛʃən/ n. 困扰, 无法摆脱的思想(或情感) 形容词: obsessional 副 词: obsessionally
A13: 12 | B13: leaflet | C13: =VLOOKUP(B13,Sheet1!$A:$B,2,0) -> /'liːflɪt//'liflət/ n. 传单, 散页印刷品 时 态: leafletedalso leafletted leafletingleafletting leafletsleaflets
... A148: 147 | B148: penis | C148: =VLOOKUP(B148,Sheet1!$A:$B,2,0) -> /'piːnɪs//'pinɪs/ n. 阴茎
A149: 148 | B149: Br. | C149: Br. is a written abbreviation for (书面缩略 =) British.
A150: 149 | B150: wit | C150: =VLOOKUP(B150,Sheet1!$A:$B,2,0) -> /wɪt//wɪt/ n. 智力；才智；智慧 时 态: wist witting first and third person singular present tense wot
A151: 150 | B151: lb | C151: =VLOOKUP(B151,Sheet1!$A:$B,2,0) -> abbr. 救生船（Lifeboat） lbabbr. Lebanon 黎巴嫩
A152: 151 | B152: psychology | C152: =VLOOKUP(B152,Sheet1!$A:$B,2,0) -> /saɪ'kɒlədʒɪ//saɪ'kɑlədʒi/ - n. 心理学 - 心理; 心理特点
A153: 152 | B153: cord | C153: =VLOOKUP(B153,Sheet1!$A:$B,2,0) -> /kɔːd//kɔrd/ - n. 束缚；绳索 - vt. 用绳子捆绑 时 态: corded, cording, cords 名 词: corder
A154: 153 | B154: Feb. | C154: =VLOOKUP(B154,Sheet1!$A:$B,2,0) -> abbr. February 二月
A155: 154 | B155: rod | C155: =VLOOKUP(B155,Sheet1!$A:$B,2,0) -> /rɒd//rɑd/ n. 竿, 杆, 棒
A156: 155 | B156: accountable | C156: =VLOOKUP(B156,Sheet1!$A:$B,2,0) -> /ə'kaʊntəb(ə)l//ə'kaʊntəbl/ adj. 负有责任的, 应对自己的行为做出说明的 名 词: accountability or 副 词: accountably
A157: 156 | B157: batter | C157: =VLOOKUP(B157,Sheet1!$A:$B,2,0) -> /'bætə//'bætɚ/ - n. 击球手；（用鸡蛋、牛奶、面粉等调成的）糊状物；墙面的倾斜 - vt. 猛击；打坏；使向上倾斜 - vi. 接连猛击；向上倾斜 时 态: battered, battering, batters...
A158: 157 | B158: pro | C158: =VLOOKUP(B158,Sheet1!$A:$B,2,0) -> /prəʊ//pro/ - adv. 赞成地 - n. 赞成者；赞成的意见 - prep. 赞成 Pro脯氨酸 PROabbr. Public Record Office 档案局( PROabbr. Public Record Office 〈英〉档案局(
A159: 158 | B159: cynical | C159: =VLOOKUP(B159,Sheet1!$A:$B,2,0) -> /'sɪnɪk(ə)l//'sɪnɪkl/ adj. 愤世嫉俗的；冷嘲的 副 词: cynically 名 词: cynicalness
A160: 159 | B160: paradise | C160: =VLOOKUP(B160,Sheet1!$A:$B,2,0) -> /'pærədaɪs//'pærə'daɪs/ n. 天堂 形容词: paradisiacal 副 词: paradisiacally or
A161: 160 | B161: tablet | C161: =VLOOKUP(B161,Sheet1!$A:$B,2,0) -> /'tæblɪt//'tæblət/ - n. 药片 - (木、竹)简; 碑, 牌匾 时 态: tableted, tableting, tablets
... A222: 221 | B222: nut | C222: =VLOOKUP(B222,Sheet1!$A:$B,2,0) -> /nʌt//nʌt/ - n. 干果, 坚果 - 螺母, 螺帽 - 头 NUTabbr. National Union of Teachers全国教师联合会 NUTabbr. National Union of Teachers 〈英〉全国教师联合会 时 态: nutted, nutting, nuts 名 词: nutter...
A223: 222 | B223: carbon dioxide | C223: N-UNCOUNT 不可数名词 二氧化碳
A224: 223 | B224: clip | C224: =VLOOKUP(B224,Sheet1!$A:$B,2,0) -> /klɪp//klɪp/ - vt. 修剪；夹牢；痛打 - vi. 修剪 - n. 夹子；修剪；回形针 CLIP - abbr. Cellular Logic Image Processor 单元逻辑映象处理器 - Compiler Language for Information Processing 信息处理用的编译程序语言 - Computer Layout Installation Planner 计算机布局安装规划程序 时 态: clipped, clipping, clips...
A225: 224 | B225: gardener | C225: =VLOOKUP(B225,Sheet1!$A:$B,2,0) -> /'ɡɑːdənə//'gɑrdənɚ/ n. 花匠；园丁；园艺家
A226: 225 | B226: bait | C226: =VLOOKUP(B226,Sheet1!$A:$B,2,0) -> /beɪt//bet/ - n. (钓鱼等用的)饵, 诱饵 - vt. 装饵于 - 故意激怒 时 态: baited, baiting, baits 名 词: baiter
A227: 226 | B227: attendant | C227: =VLOOKUP(B227,Sheet1!$A:$B,2,0) -> /ə'tend(ə)nt//ə'tɛndənt/ - n. 服务人员, 侍者, 随从 - 伴随物 - adj. 伴随的, 随之而产生的 - 护理的 副 词: attendantly
A228: 227 | B228: hurricane | C228: =VLOOKUP(B228,Sheet1!$A:$B,2,0) -> /'hʌrɪk(ə)n//'hɝəkən/ n. 飓风, (尤指西印度群岛的)旋风
A229: 228 | B229: sprinkle | C229: =VLOOKUP(B229,Sheet1!$A:$B,2,0) -> /'sprɪŋk(ə)l//'sprɪŋkl/ - n. 少量；撒，洒 - vt. 洒；微雨；散置 - vi. 洒，撒；下稀疏小雨；喷撒 时 态: sprinkled, sprinkling, sprinkles
A230: 229 | B230: scoop | C230: =VLOOKUP(B230,Sheet1!$A:$B,2,0) -> /skuːp//skup/ - n. 小铲; 小勺 - 一勺[铲]之量 - (抢先刊载、播出的)独家新闻 - vt. 用铲[勺]等挖(洞等) - 抢先报道 - 抢先获得, 胜过 时 态: scooped, scooping, scoops 名 词: scooper 名 词: scoopful...
A231: 230 | B231: relaxed | C231: =VLOOKUP(B231,Sheet1!$A:$B,2,0) -> /rɪˈlækst//rɪ'lækst/ - adj. 松懈的，放松的；不严格的，不拘束的；悠闲的，自在的 - v. relax的过去式和过去分词
A232: 231 | B232: hull | C232: =VLOOKUP(B232,Sheet1!$A:$B,2,0) -> /hʌl//hʌl/ - n. 船体, 船身 - vt. 去(谷物、豆等的)壳 Hull赫尔(①姓氏 ②Cordell, 1871 -1955, 美国政治家, 于1933 -1944任美国国务卿, 曾获1945年诺贝尔和平奖 ③英格兰东北部一港市 ④加拿大东南部一城市) 时 态: hulled, hulling, hulls 名 词: huller...
A233: 232 | B233: two-thirds | C233: QUANT 数量词 三分之二
A234: 233 | B234: petty | C234: =VLOOKUP(B234,Sheet1!$A:$B,2,0) -> /ˈpeti//ˈpɛti/ adj. 小规模的；小气的；琐碎的 Petty佩蒂(姓氏) 比较级: pettier, pettiest 副 词: pettily 名 词: pettiness
A235: 234 | B235: organism | C235: =VLOOKUP(B235,Sheet1!$A:$B,2,0) -> /'ɔːg(ə)nɪz(ə)m//'ɔrɡənɪzəm/ - n. 有机物, 有机体; 生物 - 有机体系 形容词: organismal 副 词: organismically
A236: 235 | B236: evaluate | C236: =VLOOKUP(B236,Sheet1!$A:$B,2,0) -> /ɪ'væljʊeɪt//ɪ'væljʊ'et/ vt. 评价, 估计, 估价 时 态: evaluated, evaluating, evaluates 名 词: evaluation 形容词: evaluative 名 词: evaluator
A237: 236 | B237: loot | C237: =VLOOKUP(B237,Sheet1!$A:$B,2,0) -> /luːt//lut/ - n. 掠夺品；战利品；抢劫 - vt. 抢劫，洗劫；强夺 - vi. 洗劫，掠夺；抢劫 时 态: looted, looting, loots 名 词: looter
A238: 237 | B238: mediate | C238: =VLOOKUP(B238,Sheet1!$A:$B,2,0) -> /'miːdɪeɪt//'midɪet/ - vi. 调解；斡旋；居中 - vt. 调停；传达 - adj. 间接的；居间的 时 态: mediated, mediating, mediates 副 词: mediately
A239: 238 | B239: ugly | C239: =VLOOKUP(B239,Sheet1!$A:$B,2,0) -> /'ʌglɪ//'ʌɡli/ adj. 丑陋的；令人厌恶的；邪恶的 比较级: uglier, ugliest 副 词: uglily 名 词: ugliness
A240: 239 | B240: syndrome | C240: =VLOOKUP(B240,Sheet1!$A:$B,2,0) -> /'sɪndrəʊm//'sɪndrəm/ - n. 综合征 - (某种条件下有共同特征的)一系列表现(事件、举动等) 形容词: syndromic
A241: 240 | B241: amusing | C241: =VLOOKUP(B241,Sheet1!$A:$B,2,0) -> /ə'mjuːzɪŋ//ə'mjuzɪŋ/ adj. 有趣的, 好玩的, 逗人笑的 副 词: amusingly 名 词: amusingness
A242: 241 | B242: profound | C242: =VLOOKUP(B242,Sheet1!$A:$B,2,0) -> /prə'faʊnd//prə'faʊnd/ - adj. 深度的; 深切的; 深远的 - 知识渊博的, 见解深刻的, 深奥的 比较级: profounder, profoundest 副 词: profoundly 名 词: profoundness...
A243: 242 | B243: fantastic | C243: =VLOOKUP(B243,Sheet1!$A:$B,2,0) -> /fæn'tæstɪk//fæn'tæstɪk/ - adj. 荒诞的, 奇异的, 古怪的 - 极大的, 异乎寻常的 - 极好的, 极出色的, 了不起的 名 词: fantasticality 副 词: fantastically 名 词: fantasticalness...
A244: 243 | B244: quest | C244: =VLOOKUP(B244,Sheet1!$A:$B,2,0) -> /kwest//kwɛst/ - n. 追求；寻找 - vi. 寻找；追求 - vt. 探索 时 态: quested, questing, quests 名 词: quester
A245: 244 | B245: risky | C245: =VLOOKUP(B245,Sheet1!$A:$B,2,0) -> /'rɪskɪ//'rɪski/ adj. 危险的；冒险的；（作品等）有伤风化的 比较级: riskier, riskiest 名 词: riskiness
... A417: 416 | B417: damn | C417: =VLOOKUP(B417,Sheet1!$A:$B,2,0) -> /dæm//dæm/ - vt. 谴责；罚…下地狱 - vi. 谴责 - n. 诅咒；一点 - adj. 可恶的 - adv. 非常 - int. 讨厌 时 态: damned, damning, damns 副 词: damningly
A418: 417 | B418: police station | C418: N-COUNT 可数名词 警察（分）局；派出所
A419: 418 | B419: legacy | C419: =VLOOKUP(B419,Sheet1!$A:$B,2,0) -> /'legəsɪ//'lɛgəsi/ - n. 遗产, 遗赠物 - 遗留之物
A420: 419 | B420: forge | C420: =VLOOKUP(B420,Sheet1!$A:$B,2,0) -> /fɔːdʒ//fɔrdʒ/ - vt. 锻造 - 伪造, 仿造 - vi. 突然向前 - n. 锻造车间; 铁匠铺 - 熔铁炉 时 态: forged, forging, forges 名 词: forgeability 形容词: forgeable 名 词: forger...
A421: 420 | B421: diverse | C421: =VLOOKUP(B421,Sheet1!$A:$B,2,0) -> /daɪ'vɜːs//daɪ'vɝs/ adj. 不同的, 多种多样的 副 词: diversely 名 词: diverseness
A422: 421 | B422: progressive | C422: =VLOOKUP(B422,Sheet1!$A:$B,2,0) -> /prə'gresɪv//prə'ɡrɛsɪv/ - adj. 不断前进的, 有进展的, 逐渐上升的 - 进步的, 先进的 副 词: progressively 名 词: progressiveness
A423: 422 | B423: deploy | C423: =VLOOKUP(B423,Sheet1!$A:$B,2,0) -> /dɪ'plɒɪ//dɪ'plɔɪ/ vt. (尤指军事行动)使展开; 施展; 部署 时 态: deployed, deploying, deploys 名 词: deployability 形容词: deployable 名 词: deployer 名 词: deployment...
A424: 423 | B424: Frenchwoman | C424: =VLOOKUP(B424,Sheet1!$A:$B,2,0) -> /'frentʃ,wumən/ n. 法国女人
A425: 424 | B425: pad | C425: =VLOOKUP(B425,Sheet1!$A:$B,2,0) -> /pæd//pæd/ - n. 衬垫；护具；便笺簿；填补 - vi. 步行；放轻脚步走 - vt. 填补；走 PAD包装拆器 时 态: padded, padding, pads 形容词: padless 名 词: padder...
A426: 425 | B426: grill | C426: =VLOOKUP(B426,Sheet1!$A:$B,2,0) -> /grɪl//ɡrɪl/ - vt. 烧，烤；烤问 - vi. 烧，烤；严加盘问 - n. 烤架，铁格子；烤肉 时 态: grilled, grilling, grills 名 词: griller
A427: 426 | B427: commentary | C427: =VLOOKUP(B427,Sheet1!$A:$B,2,0) -> /ˈkɔmentəri//'kɑməntɛri/ - n. 实况报道, 解说词 - 评论; 评注 形容词: commentarial
A428: 427 | B428: confederation | C428: =VLOOKUP(B428,Sheet1!$A:$B,2,0) -> /kənfedə'reɪʃ(ə)n//kən,fɛdə'reʃən/ n. 联盟；同盟；邦联 名 词: confederationism 名 词: confederationist
A429: 428 | B429: aggregate | C429: =VLOOKUP(B429,Sheet1!$A:$B,2,0) -> /'ægrɪgət//'æɡrɪɡət/ - n. 〈正〉数, 总计 - vt. 总计达… - vt. & vi. (使)聚集 时 态: aggregated, aggregating, aggregates 副 词: aggregately 名 词: aggregation 形容词: aggregative 名 词: aggregator...
A430: 429 | B430: sway | C430: =VLOOKUP(B430,Sheet1!$A:$B,2,0) -> /sweɪ//swe/ - vt. 使摇动；统治；影响 - vi. 摇摆；影响 - n. 摇摆；统治；影响 时 态: swayed, swaying, sways 名 词: swayer 副 词: swayingly
... A545: 544 | B545: aboard | C545: =VLOOKUP(B545,Sheet1!$A:$B,2,0) -> /ə'bɔːd//ə'bɔrd/ - adv. 在火车上；在飞机上；在船上 - prep. 在…上
A546: 545 | B546: estate agent | C546: N-COUNT 可数名词 房地产经纪人
A547: 546 | B547: humiliation | C547: =VLOOKUP(B547,Sheet1!$A:$B,2,0) -> /hju:ˌmɪli:ˈeɪʃən//hjʊ,mɪlɪ'eʃən/ n. 丢脸;羞辱;耻辱；蒙羞
A548: 547 | B548: stump | C548: =VLOOKUP(B548,Sheet1!$A:$B,2,0) -> /stʌmp//stʌmp/ - n. 树桩；残余部分；假肢 - vt. 砍伐；使为难；在…作巡回政治演说 - vi. 笨重地行走；发表竞选演说 时 态: stumped, stumping, stumps 名 词: stumper 名 词: stumpiness 形容词: stumpy...
A549: 548 | B549: hollow | C549: =VLOOKUP(B549,Sheet1!$A:$B,2,0) -> /'hɒləʊ//'hɑlo/ - adj. 空的；凹的；虚伪的；中空的，空腹的 - n. 洞；山谷；窟窿 - vt. 使成为空洞 - vi. 形成空洞 - adv. 无用地；彻底地 比较级: hollower, hollowest 副 词: hollowly 名 词: hollowness...
A550: 549 | B550: groan | C550: =VLOOKUP(B550,Sheet1!$A:$B,2,0) -> /grəʊn//ɡron/ - vi. 呻吟；抱怨；发吱嘎声 - vt. 呻吟；抱怨 - n. 呻吟；叹息；吱嘎声 时 态: groaned, groaning, groans 名 词: groaner 副 词: groaningly...
A551: 550 | B551: fibre | C551: =VLOOKUP(B551,Sheet1!$A:$B,2,0) -> /'faibə//ˈfaɪbɚ/ n. 纤维；纤维制品
A552: 551 | B552: primarily | C552: =VLOOKUP(B552,Sheet1!$A:$B,2,0) -> /'praɪm(ə)rɪlɪ//praɪ'mɛrəli/ - adv. 主要地, 首要地; 本来 - 首先
A553: 552 | B553: retort | C553: =VLOOKUP(B553,Sheet1!$A:$B,2,0) -> /rɪ'tɔːt//rɪ'tɔrt/ - vt. 反驳 - n. 反驳, 回嘴 - 反驳的回答 时 态: retorted, retorting, retorts 名 词: retorter
A554: 553 | B554: limb | C554: =VLOOKUP(B554,Sheet1!$A:$B,2,0) -> /lɪm//lɪm/ - n. 肢，臂；枝干；分支 - vt. 切断…的手足；从…上截下树枝 时 态: limbed, limbing, limbs
A555: 554 | B555: millionaire | C555: =VLOOKUP(B555,Sheet1!$A:$B,2,0) -> /mɪljə'neə//ˌmɪljə'nɛr/ - n. 百万富翁, 大富翁 - 大财主, 有钱人
A556: 555 | B556: precise | C556: =VLOOKUP(B556,Sheet1!$A:$B,2,0) -> /prɪ'saɪs//prɪ'saɪs/ adj. 精确的；明确的；严格的 名 词: preciseness
A557: 556 | B557: cattle | C557: =VLOOKUP(B557,Sheet1!$A:$B,2,0) -> /'kæt(ə)l//'kætl/ n. (总称)牛, 牲口
A558: 557 | B558: weird | C558: =VLOOKUP(B558,Sheet1!$A:$B,2,0) -> /wɪəd//wɪrd/ - adj. 怪诞的; 神秘而可怕的; 超然的 - 古怪的; 离奇的 比较级: weirder, weirdest 副 词: weirdly 名 词: weirdness
... A665: 664 | B665: broadcaster | C665: =VLOOKUP(B665,Sheet1!$A:$B,2,0) -> /'brɔdkæstɚ/ n. 播送设备,广播员,撒播物，广播公司
A666: 665 | B666: Midlands | C666: N-PROPER-COLL 专有集合名词 (尤指英格兰的)中部地区
A667: 666 | B667: solemn | C667: =VLOOKUP(B667,Sheet1!$A:$B,2,0) -> /'sɒləm//'sɑləm/ - adj. 严肃的 - 庄重的, 郑重的 - 庄严的; 隆重的 副 词: solemnly 名 词: solemnness
A668: 667 | B668: albeit | C668: =VLOOKUP(B668,Sheet1!$A:$B,2,0) -> /ɔːl'biːɪt//ˌɔl'biɪt/ conj. 即使；虽然
A669: 668 | B669: nationwide | C669: =VLOOKUP(B669,Sheet1!$A:$B,2,0) -> /'neɪʃ(ə)nwaɪd//ˌneʃn'waɪd/ adj. & adv. 全国范围的;全国性的;在全国
A670: 669 | B670: insistence | C670: =VLOOKUP(B670,Sheet1!$A:$B,2,0) -> /ɪn'sɪst(ə)ns/ n. 坚持
A671: 670 | B671: dismissal | C671: =VLOOKUP(B671,Sheet1!$A:$B,2,0) -> /dɪs'mɪsl//dɪs'mɪsl/ n. 解雇, 免职, 开除
A672: 671 | B672: dizzy | C672: =VLOOKUP(B672,Sheet1!$A:$B,2,0) -> /'dɪzɪ//'dɪzi/ - adj. 晕眩的；昏乱的；使人头晕的；心不在焉的；[口]愚蠢的 - vt. 使头晕眼花；使混乱；使茫然 比较级: dizzier, dizziest 副 词: dizzily 名 词: dizziness 副 词: dizzyingly...
A673: 672 | B673: aviation | C673: =VLOOKUP(B673,Sheet1!$A:$B,2,0) -> /eɪvɪ'eɪʃ(ə)n//ˌevɪ'eʃən/ n. 航空；飞行术；飞机制造业
A674: 673 | B674: drunk | C674: =VLOOKUP(B674,Sheet1!$A:$B,2,0) -> /drʌŋk//drʌŋk/ adj. 醉的; 陶醉的
A675: 674 | B675: manifesto | C675: =VLOOKUP(B675,Sheet1!$A:$B,2,0) -> /mænɪ'festəʊ//ˌmænɪ'fɛsto/ n. 宣言
A676: 675 | B676: fascism | C676: =VLOOKUP(B676,Sheet1!$A:$B,2,0) -> /'fæʃɪz(ə)m//'fæ'ʃɪzəm/ n. 法西斯主义；极端国家主义 Fascismn. 法西斯主义 形容词: fascistic
A677: 676 | B677: underestimate | C677: =VLOOKUP(B677,Sheet1!$A:$B,2,0) -> /ʌndər'estɪmeɪt//ʌndɚ'ɛstəmet/ - vt. 对…估计不足, 低估 - n. 估计不足, 低估 时 态: underestimated, underestimating, underestimates 名 词: underestimation
A678: 677 | B678: overlook | C678: =VLOOKUP(B678,Sheet1!$A:$B,2,0) -> /əʊvə'lʊk//ˌovɚ'lʊk/ - vt. 忽视 - 原谅 - 监督, 管理 - 俯视 时 态: overlooked, overlooking, overlooks
... A775: 774 | B775: inappropriate | C775: =VLOOKUP(B775,Sheet1!$A:$B,2,0) -> /ɪnə'prəʊprɪət//'ɪnə'proprɪət/ adj. 不恰当的, 不适宜的 副 词: inappropriately 名 词: inappropriateness
A776: 775 | B776: personal computer | C776: N-COUNT 可数名词 个人电脑（缩略形式为 PC）
A777: 776 | B777: minimal | C777: =VLOOKUP(B777,Sheet1!$A:$B,2,0) -> /'mɪnɪm(ə)l//'mɪnɪməl/ adj. 〈正式〉最小的; 极少的 名 词: minimality 副 词: minimally
A778: 777 | B778: nil | C778: =VLOOKUP(B778,Sheet1!$A:$B,2,0) -> /nɪl//nɪl/ n. 无，零 形容词: nil
A779: 778 | B779: compulsory | C779: =VLOOKUP(B779,Sheet1!$A:$B,2,0) -> /kəm'pʌls(ə)rɪ//kəm'pʌlsəri/ adj. 必须做的, 强制性的 副 词: compulsorily 名 词: compulsoriness
A780: 779 | B780: restraint | C780: =VLOOKUP(B780,Sheet1!$A:$B,2,0) -> /rɪ'streɪnt//rɪ'strent/ - n. 抑制, 遏制, 管制, 约束 - 克制物, 管制措施, 约束力 - 克制, 节制, 适度
A781: 780 | B781: mandate | C781: =VLOOKUP(B781,Sheet1!$A:$B,2,0) -> /'mændeɪt//'mændet/ - n. (选民对选出的代表、议会等的)授权 - (上级官员对下级官员下达的)正式命令 - vt. 将(某地)委托某国管理 - 授权(某人)根据委托统治权(做某事) 时 态: mandated, mandating, mandates 名 词: mandator...
...

Sheet Sheet1
A1: appal | B1: /ə'pɔːl//əˈpɔl/ vt. 使惊骇; 使充满恐惧
A2: contractor | B2: /kən'træktə//kən'træktɚ/ n. (建筑、监造中的)承包人
A3: spectacle | B3: /'spektək(ə)l//'spɛktəkl/ - n. 壮观的场面或景象 - 可笑的事物; 愚蠢的景象 - 眼镜
A4: apt | B4: /æpt//æpt/ - adj. 易于…的, 有…倾向的 - 恰当的, 适宜的 - 聪明的, 灵巧的 APTabbr. Advanced Passenger Train高级旅客列车 副 词: aptly 名 词: aptness
A5: reactor | B5: /rɪ'æktə//rɪ'æktɚ/ n. 反应堆；反应器；起反应的人
A6: old-fashioned | B6: /'əuld'fæʃənd//ˈoldˈfæʃənd/ adj. 老式的,过时的,守旧的
A7: thief | B7: /θiːf//θif/ n. 小偷，贼
A8: snatch | B8: /snætʃ//snætʃ/ - n. 抢夺；小量；抓举 - vt. 夺得；抽空做；及时救助 - vi. 抢走；很快接受 时 态: snatched, snatching, snatches 名 词: snatcher
A9: mathematical | B9: /mæθ(ə)'mætɪk(ə)l//ˌmæθə'mætɪkl/ - adj. 数学的, 数学上的 - 精确的 副 词: mathematically
A10: technician | B10: /tek'nɪʃ(ə)n//tɛk'nɪʃən/ n. 技术人员, 专家; 技巧好的人
A11: groove | B11: /gruːv//ɡruv/ - n. 凹槽，槽；最佳状态；惯例 - vt. 开槽于 - vi. 形成沟槽 时 态: grooved, grooving, grooves
A12: gloom | B12: /gluːm//ɡlum/ - n. 昏暗, 阴暗 - 忧郁, 沮丧, 失望 时 态: gloomed, glooming, glooms
... A2075: insult | B2075: /ɪn'sʌlt//ɪn'sʌlt/ - vt. 侮辱, 冒犯 - n. 侮辱, 辱骂, 侮辱性的言论 时 态: insulted, insulting, insults 名 词: insulter 副 词: insultingly
A2076: j礖_x0014_0 ★★☆☆☆20.lrc&U_x0005__x0005__x0006__x0006_@_x0006_20.lrc袄ot[ti:单词风暴语音文件(★★☆☆☆20)
A2077: sue | B2077: /s(j)uː//su/ vt. & vi. (为要求赔偿损失而)起诉, 控告, 和…打官司 时 态: sued, suing, sues 名 词: suer
A2078: doubtful | B2078: /'daʊtfʊl//'daʊtfəl/ - adj. 难以预测的, 未定的 - 怀疑的, 可疑的 副 词: doubtfully 名 词: doubtfulness
A2079: underway | B2079: /'ʌndə'weɪ//ˌʌndɚ'we/ adj. 在进行中的
A2080: prone | B2080: /prəʊn//pron/ - adj. 易于…的; 很可能…的 - 俯卧的 副 词: pronely 名 词: proneness
A2081: brokerage | B2081: /'brəʊk(ə)rɪdʒ//'brokərɪdʒ/ - n. 经纪业 - 佣金,手续费,经纪费
A2082: brutal | B2082: /'bruːt(ə)l//'brutl/ adj. 残忍的；野蛮的，不讲理的 副 词: brutally
A2083: lifetime | B2083: /'laɪftaɪm//'laɪftaɪm/ - n. 一生；寿命；终生；使用期 - adj. 一生的；终身的
A2084: dense | B2084: /dens//dɛns/ adj. 浓厚的；稠密的；愚钝的 比较级: denser, densest 副 词: densely 名 词: denseness
A2085: exit | B2085: /'eksɪt//'ɛɡzɪt/ - n. 出口, 通道, 安全门 - 退出, 退场 - vi. 离开; 退场 时 态: exited, exiting, exits
A2086: asthma | B2086: /'æsmə//'æzmə/ n. 〈医〉气喘; 哮喘 形容词: asthmatic 副 词: asthmatically
A2087: sunlight | B2087: /'sʌnlaɪt//'sʌnlaɪt/ n. 日光
A2088: quarrel | B2088: /'kwɒr(ə)l//'kwɔrəl/ - n. 争吵, 不和, 口角 - 抱怨…的原因[理由] - vi. 争吵, 争辩 - 不同意; 挑剔 时 态: quarreled, quarrelled quarreling, quarrelling quarrels, quarrels 名 词: quarreler or...
... A2818: singing | B2818: /ˈsɪŋɪŋ//'sɪŋɪŋ/ - n. 歌声；歌唱；耳鸣；振鸣 - adj. 唱歌的；音乐般的 - v. 唱歌（sing的ing形式）
A2819: caf??
A2820: misleading | B2820: /mɪsˈli:dɪŋ//ˌmɪs'lidɪŋ/ adj. 欺骗的;误导性的 副 词: misleadingly
A2821: hopefully | B2821: /'həʊpfʊlɪ//'hopfəli/ adv. 怀有希望地;如果顺利的话,可望
A2822: corridor | B2822: /'kɒrɪdɔː//'kɔrɪdɔr/ n. 走廊
A2823: hound | B2823: /haʊnd//haʊnd/ - vt. 追猎；烦扰；激励 - n. 猎犬；卑劣的人 时 态: hounded, hounding, hounds 名 词: hounder
A2824: limp | B2824: /lɪmp//lɪmp/ - n. 跛行 - vi. 一瘸一拐地走 - 困难地航行 - adj. 无力的; 无生气的; 易弯的; 松软的 LIMPabbr. Language-Independent Macro Processor 独立于语言的宏加工程序 时 态: limped, limping, limps 副 词: limply 名 词: limpness...
A2825: bureaucrat | B2825: /'bjʊərəkræt//'bjʊrəkræt/ - n. 官僚,官僚主义者,官僚作风的人 - n. 官僚语言 - n. 官僚主义 - n. 官僚主义者 形容词: bureaucratic 副 词: bureaucratically...
A2826: conversion | B2826: /kən'vɜːʃ(ə)n//kən'vɝʒn/ - n. 变换, 转化 - (宗教、信仰等)彻底改变; 皈依 形容词: conversional or
A2827: journalism | B2827: /'dʒɜːn(ə)lɪz(ə)m//'dʒɝnl'ɪzəm/ n. 新闻业
A2828: slap | B2828: /slæp//slæp/ - vt. 掌击；拍击；掴…的耳光；侮辱 - n. 掌击；掴；侮辱；拍打声 - vi. 掴；拍击 - adv. 直接地；猛然地；恰好 时 态: slapped, slapping, slaps 名 词: slapper...
A2829: impatient | B2829: /ɪm'peɪʃ(ə)nt//ɪm'peʃnt/ - adj. 不耐烦的, 急躁的 - 热切的, 急切的 副 词: impatiently
A2830: continuous | B2830: /kən'tɪnjʊəs//kən'tɪnjʊəs/ adj. 连续的, 没有中断的 副 词: continuously 名 词: continuousness
A2831: imposing | B2831: /ɪm'pəʊzɪŋ//ɪm'pozɪŋ/ adj. 庄严的, 仪表堂堂的, 令人印象深刻的 副 词: imposingly
... A3022: bully | B3022: /'bʊlɪ//'bʊli/ vt. 恐吓, 威逼

Sheet sheet2
A1: appal | B1: v.惊骇
A2: oust | B2: vt.剥夺, 取代, 驱逐
A3: purse | B3: n.钱包
A4: glare | B4: n.眩目的光, 显眼, 怒目而视, (冰等的表面)光滑的表面
A5: hobby | B5: n.业余爱好
A6: excellence | B6: n.优秀, 卓越, 优点, 美德
A7: contractor | B7: n.订约人, 承包人
A8: format | B8: n.开本, 版式, 形式, 格式
A9: gloom | B9: n.阴暗, 阴沉
A10: constituent | B10: n.委托人, 要素
A11: reactor | B11: n.反应堆
A12: ass | B12: n.驴, 笨人, 臀部
... A2047: FBI | B2047: FBI
A2048: j礖_x0014_0 ★★☆☆☆20.lrc&U_x0005__x0005__x0006__x0006_@_x0006_20.lrc袄ot[ti:单词风暴语音文件(★★☆☆☆20)
A2049: hover | B2049: vi. 盘旋，翱翔；徘徊 n. 徘徊；盘旋；犹豫 vt. 孵；徘徊在…近旁
A2050: glove | B2050: n.手套
A2051: team-mate | B2051: team-mate
A2052: brick | B2052: n.砖, 砖块, 砖形物(如茶砖,冰砖等), <口>心肠好的人
A2053: compose | B2053: v.组成, 写作, 排字, (使)安定, 调解
A2054: ooh | B2054: int. （表示惊讶、欣喜、痛苦等）嚯，呵
A2055: sunlight | B2055: n.日光, 阳光, 日照
A2056: power station | B2056: n.发电所
A2057: asthma | B2057: n.〖医〗哮喘
A2058: surgical | B2058: adj.外科的, 外科医生的, 手术上的
A2059: spine | B2059: n.脊骨, 书脊, 地面隆起地带, 中心, 剌
A2060: custom | B2060: n.习惯, 风俗, <动词单用>海关, (封建制度下)定期服劳役, 缴纳租税, 自定义, <偶用作>关税
... A3048: contradiction | B3048: n.反驳, 矛盾
