Workbook

Sheet 四星词频（带音标与简明义项）
A1: # | B1: 单词 | C1: 解释
A2: 1 | B2: district | C2: =VLOOKUP(B2,sheet1!$A:$B,2,0) -> /'dɪstrɪkt//'dɪstrɪkt/ n. 区域；行政区；地方 时 态: districted, districting, districts 副 词: districtwide
A3: 2 | B3: tear | C3: =VLOOKUP(B3,sheet1!$A:$B,2,0) -> /teə//tɛr/ - vt. 撕破，撕裂；使分裂；使精神不安；折磨 - vi. 撕破；飞奔；被撕破 - n. 扯；扯破的洞 时 态: tore torn tearing, tears 名 词: tearer...
A4: 3 | B4: balance | C4: =VLOOKUP(B4,sheet1!$A:$B,2,0) -> /'bæl(ə)ns//'bæləns/ - n. 平衡；匀称；余额 - vt. 使平衡；结算；使相称 - vi. 保持平衡；相称；抵销 Balance天秤星座 时 态: balanced, balancing, balances...
A5: 4 | B5: cash | C5: =VLOOKUP(B5,sheet1!$A:$B,2,0) -> /kæʃ//kæʃ/ - n. 现款，现金 - vt. 将…兑现；支付现款 时 态: cashed, cashing, cashes 形容词: cashless
A6: 5 | B6: gay | C6: =VLOOKUP(B6,sheet1!$A:$B,2,0) -> /geɪ//ɡe/ - adj. 快乐的, 欢快的; 轻松的, 愉快的 - 轻率的, 不假思索的; 放荡的 - 同性恋的 Gay盖伊(女子名) 比较级: gayer, gayest 名 词: gayness
A7: 6 | B7: damage | C7: =VLOOKUP(B7,sheet1!$A:$B,2,0) -> /'dæmɪdʒ//'dæmɪdʒ/ - vt. & vi. 损害, 毁坏, 加害于 - n. 损失, 损害, 损毁 - 损害赔偿金 时 态: damaged, damaging, damages 名 词: damageability 形容词: damageable 副 词: damagingly...
A8: 7 | B8: entry | C8: =VLOOKUP(B8,sheet1!$A:$B,2,0) -> /'entri//ˈɛntri/ n. 入口；进入；登记；条目；对土地的侵占；[商]报关手续
A9: 8 | B9: long-term | C9: =VLOOKUP(B9,sheet1!$A:$B,2,0) -> /ˈlɔ:ŋˈtɜ:m//'lɔŋtɝm/ adj. 长期的
A10: 9 | B10: myself | C10: =VLOOKUP(B10,sheet1!$A:$B,2,0) -> /maɪ'self//maɪ'sɛlf/ pron. 我自己；我亲自；我的正常的健康状况和正常情绪
A11: 10 | B11: particular | C11: =VLOOKUP(B11,sheet1!$A:$B,2,0) -> /pə'tɪkjʊlə//pɚ'tɪkjəlɚ/ - adj. 特定的, 某一的 - 特殊的, 特别的, 特有的 - (过分)讲究的, 挑剔的 - 详细的, 详尽的 - n. 详情; 细目
A12: 11 | B12: aim | C12: =VLOOKUP(B12,sheet1!$A:$B,2,0) -> /eɪm//em/ - vt. & vi. (以…)瞄准; 针对 - vi. 以…为目标[目的] - n. 瞄准 - 目标, 目的 AIMabbr. Aerial Intercept Missile 航空拦截导弹, 空中拦截导弹 AIMabbr. Aerial (Air) Intercept Missile 航空[空中]拦截导弹 时 态: aimed, aiming, aims...
A13: 12 | B13: nature | C13: =VLOOKUP(B13,sheet1!$A:$B,2,0) -> /'neɪtʃə//'netʃɚ/ n. 自然；性质；种类；本性
... A987: 986 | B987: influence | C987: =VLOOKUP(B987,sheet1!$A:$B,2,0) -> /'ɪnflʊəns//'ɪnfluəns/ - n. 影响; 感化力 - 势力, 权势 - 产生影响的人[事物] - vt. 影响, 感化 时 态: influenced, influencing, influences 形容词: influenceable 名 词: influencer...

Sheet sheet1
A1: bag | B1: /bæg//bæɡ/ - n. 袋, 包 - vt. 装袋 - vi. 宽松地下垂, 鼓胀 时 态: bagged, bagging, bags 名 词: bagful 名 词: bagger
A2: shape | B2: /ʃeɪp//ʃep/ - n. 形状；具体化；模型；身材 - vt. 塑造，使成形；形成；使符合 - vi. 成形；形成；成长 SHAPEabbr. Supersonic High Altitude Parachute Experiment 超音速高空降落伞试验 时 态: shaped, shaping, shapes 形容词: shapable or 形容词: shaped 名 词: shaper...
A3: fifteenth | B3: /fɪf'tiːnθ//'fɪf'tinθ/ - adj. (与the连用)第十五的,第十五个的 - 十五分之一的 - n. (与the连用)第十五(个);月的第十五日 - 十五分之一 副 词: fifteenth...
A4: treat | B4: /triːt//trit/ - n. 款待, 招待 - 乐事, 乐趣 - vt. 对待, 看待 - 处理 - 探讨, 讨论, 论述 - 把…看作 - 治疗 - vt. & vi. 请客, 款待 TREATabbr. Transient Reactor Test Facility 研究过渡过程用的实验性反应堆 时 态: treated, treating, treats 名 词: treater...
A5: diet | B5: /'daɪət//'daɪət/ - n. 日常饮食 - 规定饮食 - vt. & vi. (使)节制饮食 时 态: dieted, dieting, diets 名 词: dieter
A6: gold | B6: /gəʊld//ɡold/ - n. 金, 黄金 - 金色 - adj. 金(制)的 - 金色的
A7: wonderful | B7: /'wʌndəfʊl//'wʌndɚfl/ adj. 极好的, 精彩的, 绝妙的 副 词: wonderfully 名 词: wonderfulness
A8: anyone | B8: /'enɪwʌn//'ɛnɪ'wʌn/ pron. 任何人；任何一个
A9: manager | B9: /'mænɪdʒə//'mænɪdʒɚ/ n. 经理；管理人员 名 词: managership
A10: independence | B10: /ɪndɪ'pend(ə)ns//ˌɪndɪ'pɛndəns/ n. 独立, 自主, 自立
A11: horse | B11: /hɔːs//hɔrs/ - n. 马；骑兵；脚架；[俚]海洛因 - vt. 使骑马；系马于；[口]捉弄 - vi. 骑马；[口]作弄人 时 态: horsed, horsing, horses
A12: throughout | B12: /θruː'aʊt//θrʊ'aʊt/ - prep. (表示时间)自始至终;在…期间 - (表示区域)遍及…地域;遍及…场所 - adv. 处处 - 始终 - 在所有方面
... A986: touch | B986: /tʌtʃ//tʌtʃ/ - vt. 接触；触动；使轻度受害 - vi. 触摸；接近；涉及；提到 - n. 接触；触觉；格调；少许 时 态: touched, touching, touches 形容词: touchable 名 词: touchableness 名 词: toucher...

Sheet sheet2
A1: scale | B1: n.刻度,衡量,比例,数值范围,比例尺,天平,等级
A2: abuse | B2: n.滥用, 虐待, 辱骂, 陋习, 弊端
A3: willing | B3: adj.乐意的, 自愿的, 心甘情愿的, 反应迅速的
A4: royal | B4: adj.王室的, 皇家的, 第一流的, 高贵的
A5: channel | B5: n.海峡, 水道, 沟, 路线
A6: cry | B6: vi.哭, 流泪
A7: victim | B7: n.受害人, 牺牲者, 牺牲品
A8: otherwise | B8: adv.另外, 否则, 不同地, 别的方式
A9: image | B9: n.图象, 肖像, 偶像, 形象化的比喻, 极为相象, 映像, 典型
A10: natural | B10: adj.自然的, 自然界的, 关于自然界的, 天生的, 天赋的, 普通的, 正常的, 简单自然的
A11: relief | B11: n.(痛苦等的)减轻, (债务等的)免除, 救济, 调剂, 安慰, 浮雕, 地貌
A12: tonight | B12: adv.今晚, 今夜
... A100: investment | B100: n.投资, 可获利的东西
A101: _x0019_
A102: baby | B102: n.婴孩
A103: equipment | B103: n.装备, 设备, 器材, 装置, 铁道车辆, (一企业除房地产以外的)固定资产, 才能
A104: degree | B104: n.度数, 度, 程度, 〖律〗(罪行的)轻重, 学位, 地位, 身份, 〖数〗次数
A105: mission | B105: n.使命, 任务, 使团, 代表团
A106: whom | B106: pron.谁
A107: collect | B107: v.收集, 聚集, 集中, 搜集
A108: solution | B108: n.解答, 解决办法, 溶解, 溶液
A109: reform | B109: n.改革, 改善, 改良运动, 感化
A110: means | B110: n.手段, 方法
A111: threaten | B111: vt.恐吓, 威胁, 预示(危险), 似有发生或来临的可能, 可能来临
A112: rest | B112: n.休息, 静止, 支持物, 台, 架, 〖音〗休止符, 其余, 其他
A113: executive | B113: adj.实行的, 执行的, 行政的
... A987: commitment | B987: n. 承诺，保证；委托；承担义务；献身
